{"name":"Hadamard (patch rotation, LaSsynth)","blueAxis":"J","dims":{"maxI":2,"maxJ":2,"maxK":3},"nStab":2,"cubes":[{"kind":"worldline","i":0,"j":0,"k":0,"color":"patch","label":"patch (0,0) worldline @ t=0 — smooth(Z,blue) on J-faces, rough(X,red) on I-faces"},{"kind":"worldline","i":0,"j":0,"k":1,"color":"patch","label":"patch (0,0) worldline @ t=1 — smooth(Z,blue) on J-faces, rough(X,red) on I-faces"},{"kind":"worldline","i":0,"j":0,"k":2,"color":"patch","label":"patch (0,0) worldline @ t=2 — smooth(Z,blue) on J-faces, rough(X,red) on I-faces"},{"kind":"worldline","i":0,"j":1,"k":0,"color":"patch","label":"patch (0,1) worldline @ t=0 — smooth(Z,blue) on J-faces, rough(X,red) on I-faces"},{"kind":"worldline","i":0,"j":1,"k":1,"color":"patch","label":"patch (0,1) worldline @ t=1 — smooth(Z,blue) on J-faces, rough(X,red) on I-faces"},{"kind":"worldline","i":1,"j":0,"k":0,"color":"patch","label":"patch (1,0) worldline @ t=0 — smooth(Z,blue) on J-faces, rough(X,red) on I-faces"},{"kind":"worldline","i":1,"j":0,"k":1,"color":"patch","label":"patch (1,0) worldline @ t=1 — smooth(Z,blue) on J-faces, rough(X,red) on I-faces"},{"kind":"zseam","i":0,"j":0,"k":1,"color":"red","label":"X̄-merge seam (I-pipe) joining patches (0,0)-(1,0) @ t=1"},{"kind":"zseam","i":0,"j":1,"k":0,"color":"red","label":"X̄-merge seam (I-pipe) joining patches (0,1)-(1,1) @ t=0"},{"kind":"zseam","i":0,"j":1,"k":2,"color":"red","label":"X̄-merge seam (I-pipe) joining patches (0,1)-(1,1) @ t=2"},{"kind":"xseam","i":1,"j":0,"k":0,"color":"blue","label":"Z̄-merge seam (J-pipe) joining patches (1,0)-(1,1) @ t=0"},{"kind":"xseam","i":1,"j":0,"k":2,"color":"blue","label":"Z̄-merge seam (J-pipe) joining patches (1,0)-(1,1) @ t=2"},{"kind":"rotation","i":0,"j":0,"k":1,"color":"yellow","label":"H / patch rotation @ (0,0) t≈1 — X̄↔Z̄ boundary swap"}],"surfaces":[{"flow":0,"plane":"KI","color":"red","i":0,"j":0,"k":0,"label":"flow 0: X̄ correlation (KI) @ (0,0,0)"},{"flow":0,"plane":"KI","color":"red","i":0,"j":0,"k":1,"label":"flow 0: X̄ correlation (KI) @ (0,0,1)"},{"flow":0,"plane":"IK","color":"red","i":0,"j":0,"k":1,"label":"flow 0: X̄ correlation (IK) @ (0,0,1)"},{"flow":0,"plane":"KI","color":"red","i":0,"j":0,"k":2,"label":"flow 0: X̄ correlation (KI) @ (0,0,2)"},{"flow":0,"plane":"KI","color":"red","i":0,"j":1,"k":0,"label":"flow 0: X̄ correlation (KI) @ (0,1,0)"},{"flow":0,"plane":"IK","color":"red","i":0,"j":1,"k":0,"label":"flow 0: X̄ correlation (IK) @ (0,1,0)"},{"flow":0,"plane":"KJ","color":"blue","i":0,"j":1,"k":0,"label":"flow 0: Z̄ correlation (KJ) @ (0,1,0)"},{"flow":0,"plane":"IJ","color":"blue","i":0,"j":1,"k":0,"label":"flow 0: Z̄ correlation (IJ) @ (0,1,0)"},{"flow":0,"plane":"KI","color":"red","i":0,"j":1,"k":1,"label":"flow 0: X̄ correlation (KI) @ (0,1,1)"},{"flow":0,"plane":"KJ","color":"blue","i":0,"j":1,"k":1,"label":"flow 0: Z̄ correlation (KJ) @ (0,1,1)"},{"flow":0,"plane":"IK","color":"red","i":0,"j":1,"k":2,"label":"flow 0: X̄ correlation (IK) @ (0,1,2)"},{"flow":0,"plane":"IJ","color":"blue","i":0,"j":1,"k":2,"label":"flow 0: Z̄ correlation (IJ) @ (0,1,2)"},{"flow":0,"plane":"KI","color":"red","i":1,"j":0,"k":0,"label":"flow 0: X̄ correlation (KI) @ (1,0,0)"},{"flow":0,"plane":"JI","color":"red","i":1,"j":0,"k":0,"label":"flow 0: X̄ correlation (JI) @ (1,0,0)"},{"flow":0,"plane":"KJ","color":"blue","i":1,"j":0,"k":0,"label":"flow 0: Z̄ correlation (KJ) @ (1,0,0)"},{"flow":0,"plane":"JK","color":"blue","i":1,"j":0,"k":0,"label":"flow 0: Z̄ correlation (JK) @ (1,0,0)"},{"flow":0,"plane":"KI","color":"red","i":1,"j":0,"k":1,"label":"flow 0: X̄ correlation (KI) @ (1,0,1)"},{"flow":0,"plane":"KJ","color":"blue","i":1,"j":0,"k":1,"label":"flow 0: Z̄ correlation (KJ) @ (1,0,1)"},{"flow":0,"plane":"JI","color":"red","i":1,"j":0,"k":2,"label":"flow 0: X̄ correlation (JI) @ (1,0,2)"},{"flow":0,"plane":"JK","color":"blue","i":1,"j":0,"k":2,"label":"flow 0: Z̄ correlation (JK) @ (1,0,2)"},{"flow":1,"plane":"KJ","color":"blue","i":0,"j":0,"k":0,"label":"flow 1: Z̄ correlation (KJ) @ (0,0,0)"},{"flow":1,"plane":"KJ","color":"blue","i":0,"j":0,"k":1,"label":"flow 1: Z̄ correlation (KJ) @ (0,0,1)"},{"flow":1,"plane":"KJ","color":"blue","i":0,"j":0,"k":2,"label":"flow 1: Z̄ correlation (KJ) @ (0,0,2)"},{"flow":1,"plane":"KI","color":"red","i":0,"j":1,"k":0,"label":"flow 1: X̄ correlation (KI) @ (0,1,0)"},{"flow":1,"plane":"IK","color":"red","i":0,"j":1,"k":0,"label":"flow 1: X̄ correlation (IK) @ (0,1,0)"},{"flow":1,"plane":"KI","color":"red","i":0,"j":1,"k":1,"label":"flow 1: X̄ correlation (KI) @ (0,1,1)"},{"flow":1,"plane":"IJ","color":"blue","i":0,"j":1,"k":1,"label":"flow 1: Z̄ correlation (IJ) @ (0,1,1)"},{"flow":1,"plane":"KI","color":"red","i":0,"j":1,"k":2,"label":"flow 1: X̄ correlation (KI) @ (0,1,2)"},{"flow":1,"plane":"IK","color":"red","i":0,"j":1,"k":2,"label":"flow 1: X̄ correlation (IK) @ (0,1,2)"},{"flow":1,"plane":"KJ","color":"blue","i":0,"j":1,"k":2,"label":"flow 1: Z̄ correlation (KJ) @ (0,1,2)"},{"flow":1,"plane":"KJ","color":"blue","i":1,"j":0,"k":0,"label":"flow 1: Z̄ correlation (KJ) @ (1,0,0)"},{"flow":1,"plane":"JK","color":"blue","i":1,"j":0,"k":0,"label":"flow 1: Z̄ correlation (JK) @ (1,0,0)"},{"flow":1,"plane":"KJ","color":"blue","i":1,"j":0,"k":1,"label":"flow 1: Z̄ correlation (KJ) @ (1,0,1)"},{"flow":1,"plane":"JK","color":"blue","i":1,"j":0,"k":2,"label":"flow 1: Z̄ correlation (JK) @ (1,0,2)"},{"flow":1,"plane":"KI","color":"red","i":1,"j":1,"k":0,"label":"flow 1: X̄ correlation (KI) @ (1,1,0)"}],"ports":[{"i":0,"j":0,"k":0,"blueSel":5,"redSel":4,"label":"port @ (0,0,0) — flow0 reads X"},{"i":0,"j":0,"k":2,"blueSel":4,"redSel":5,"label":"port @ (0,0,2) — flow0 reads Z"}]}